orsopy/__init__.py
orsopy/orb2ort.py
orsopy/ort2orb.py
orsopy/fileio/__init__.py
orsopy/fileio/base.py
orsopy/fileio/data_source.py
orsopy/fileio/model_building_blocks.py
orsopy/fileio/model_complex.py
orsopy/fileio/model_language.py
orsopy/fileio/orso.py
orsopy/fileio/reduction.py
orsopy/fileio/typing_backport.py
orsopy/fileio/schema/refl_header.schema.json
orsopy/fileio/schema/refl_header.schema.yaml
orsopy/fileio/tests/__init__.py
orsopy/fileio/tests/not_orso.ort
orsopy/fileio/tests/test_base.py
orsopy/fileio/tests/test_data_source.py
orsopy/fileio/tests/test_example.ort
orsopy/fileio/tests/test_example2.ort
orsopy/fileio/tests/test_model_language.py
orsopy/fileio/tests/test_orso.py
orsopy/fileio/tests/test_reduction.py
orsopy/fileio/tests/test_schema.py
orsopy/slddb/__init__.py
orsopy/slddb/comparators.py
orsopy/slddb/constants.py
orsopy/slddb/converters.py
orsopy/slddb/database.py
orsopy/slddb/dbconfig.py
orsopy/slddb/importers.py
orsopy/slddb/material.py
orsopy/slddb/webapi.py
orsopy/slddb/element_table/__init__.py
orsopy/slddb/element_table/element.py
orsopy/slddb/element_table/masses.py
orsopy/slddb/element_table/nabs_geant4.py
orsopy/slddb/element_table/nlengths.py
orsopy/slddb/element_table/nlengths_pt.py
orsopy/slddb/element_table/xray_henke.py
orsopy/slddb/element_table/xray_nist.py
orsopy/slddb/element_table/nabs_geant4/nabs_B.npz
orsopy/slddb/element_table/nabs_geant4/nabs_B10.npz
orsopy/slddb/element_table/nabs_geant4/nabs_B11.npz
orsopy/slddb/element_table/nabs_geant4/nabs_Cd.npz
orsopy/slddb/element_table/nabs_geant4/nabs_Cd106.npz
orsopy/slddb/element_table/nabs_geant4/nabs_Cd108.npz
orsopy/slddb/element_table/nabs_geant4/nabs_Cd110.npz
orsopy/slddb/element_table/nabs_geant4/nabs_Cd111.npz
orsopy/slddb/element_table/nabs_geant4/nabs_Cd112.npz
orsopy/slddb/element_table/nabs_geant4/nabs_Cd113.npz
orsopy/slddb/element_table/nabs_geant4/nabs_Cd114.npz
orsopy/slddb/element_table/nabs_geant4/nabs_Cd116.npz
orsopy-1.2.2.dist-info/licenses/LICENSE
orsopy-1.2.2.dist-info/METADATA
orsopy-1.2.2.dist-info/WHEEL
orsopy-1.2.2.dist-info/top_level.txt
orsopy-1.2.2.dist-info/RECORD
