Metadata-Version: 2.4
Name: orsopy
Version: 1.2.2
Summary: Support library of the Open Reflectometry Standards Organization (ORSO)
Home-page: https://github.com/reflectivity/orsopy
Author: ORSO contributors (see AUTHORS.rst)
Author-email: andrew.mccluskey@ess.eu
License: MIT
Classifier: Programming Language :: Python :: 3
Classifier: License :: OSI Approved :: MIT License
Classifier: Operating System :: OS Independent
Classifier: Topic :: Scientific/Engineering
Classifier: Development Status :: 5 - Production/Stable
Requires-Python: >=3.8
License-File: LICENSE
Requires-Dist: pyyaml>=5.4.1
Dynamic: license-file
